{
  "markets": [
    {
      "id": "2680257",
      "question": "Will Canada win on 2026-06-28?",
      "category": "General",
      "endDate": "2026-06-28T19:00:00Z",
      "yesPrice": 0.375,
      "outcomes": [
        {
          "id": "2680257-0",
          "title": "Yes",
          "price": 0.375
        },
        {
          "id": "2680257-1",
          "title": "No",
          "price": 0.625
        }
      ],
      "volume": 30647807.259832386,
      "liquidity": 357316.9962,
      "lastUpdated": "2026-06-28T20:19:38.304Z"
    },
    {
      "id": "558940",
      "question": "Will Portugal win the 2026 FIFA World Cup?",
      "category": "General",
      "endDate": "2026-07-20T00:00:00Z",
      "yesPrice": 0.0575,
      "outcomes": [
        {
          "id": "558940-0",
          "title": "Yes",
          "price": 0.0575
        },
        {
          "id": "558940-1",
          "title": "No",
          "price": 0.9425
        }
      ],
      "volume": 76844219.89945422,
      "liquidity": 3635602.27306,
      "lastUpdated": "2026-06-28T20:19:38.304Z"
    },
    {
      "id": "558938",
      "question": "Will Argentina win the 2026 FIFA World Cup?",
      "category": "General",
      "endDate": "2026-07-20T00:00:00Z",
      "yesPrice": 0.2085,
      "outcomes": [
        {
          "id": "558938-0",
          "title": "Yes",
          "price": 0.2085
        },
        {
          "id": "558938-1",
          "title": "No",
          "price": 0.7915
        }
      ],
      "volume": 81141140.49285467,
      "liquidity": 8461446.94387,
      "lastUpdated": "2026-06-28T20:19:38.304Z"
    },
    {
      "id": "558934",
      "question": "Will Spain win the 2026 FIFA World Cup?",
      "category": "General",
      "endDate": "2026-07-20T00:00:00Z",
      "yesPrice": 0.1115,
      "outcomes": [
        {
          "id": "558934-0",
          "title": "Yes",
          "price": 0.1115
        },
        {
          "id": "558934-1",
          "title": "No",
          "price": 0.8885
        }
      ],
      "volume": 68842305.85844523,
      "liquidity": 8847963.98246,
      "lastUpdated": "2026-06-28T20:19:38.304Z"
    },
    {
      "id": "558937",
      "question": "Will Brazil win the 2026 FIFA World Cup?",
      "category": "General",
      "endDate": "2026-07-20T00:00:00Z",
      "yesPrice": 0.0605,
      "outcomes": [
        {
          "id": "558937-0",
          "title": "Yes",
          "price": 0.0605
        },
        {
          "id": "558937-1",
          "title": "No",
          "price": 0.9395
        }
      ],
      "volume": 62556377.14167997,
      "liquidity": 3274791.2045,
      "lastUpdated": "2026-06-28T20:19:38.305Z"
    },
    {
      "id": "2680256",
      "question": "Will South Africa vs. Canada end in a draw?",
      "category": "General",
      "endDate": "2026-06-28T19:00:00Z",
      "yesPrice": 0.455,
      "outcomes": [
        {
          "id": "2680256-0",
          "title": "Yes",
          "price": 0.455
        },
        {
          "id": "2680256-1",
          "title": "No",
          "price": 0.545
        }
      ],
      "volume": 2970798.217210988,
      "liquidity": 284728.45,
      "lastUpdated": "2026-06-28T20:19:38.305Z"
    },
    {
      "id": "2680253",
      "question": "Will South Africa win on 2026-06-28?",
      "category": "General",
      "endDate": "2026-06-28T19:00:00Z",
      "yesPrice": 0.175,
      "outcomes": [
        {
          "id": "2680253-0",
          "title": "Yes",
          "price": 0.175
        },
        {
          "id": "2680253-1",
          "title": "No",
          "price": 0.825
        }
      ],
      "volume": 2968985.8672940047,
      "liquidity": 246555.4593,
      "lastUpdated": "2026-06-28T20:19:38.305Z"
    },
    {
      "id": "558939",
      "question": "Will Germany win the 2026 FIFA World Cup?",
      "category": "General",
      "endDate": "2026-07-20T00:00:00Z",
      "yesPrice": 0.0395,
      "outcomes": [
        {
          "id": "558939-0",
          "title": "Yes",
          "price": 0.0395
        },
        {
          "id": "558939-1",
          "title": "No",
          "price": 0.9605
        }
      ],
      "volume": 72070099.23400795,
      "liquidity": 4116711.37088,
      "lastUpdated": "2026-06-28T20:19:38.305Z"
    },
    {
      "id": "558941",
      "question": "Will Netherlands win the 2026 FIFA World Cup?",
      "category": "General",
      "endDate": "2026-07-20T00:00:00Z",
      "yesPrice": 0.0515,
      "outcomes": [
        {
          "id": "558941-0",
          "title": "Yes",
          "price": 0.0515
        },
        {
          "id": "558941-1",
          "title": "No",
          "price": 0.9485
        }
      ],
      "volume": 73095816.13714851,
      "liquidity": 3031082.63744,
      "lastUpdated": "2026-06-28T20:19:38.305Z"
    },
    {
      "id": "558935",
      "question": "Will England win the 2026 FIFA World Cup?",
      "category": "General",
      "endDate": "2026-07-20T00:00:00Z",
      "yesPrice": 0.1025,
      "outcomes": [
        {
          "id": "558935-0",
          "title": "Yes",
          "price": 0.1025
        },
        {
          "id": "558935-1",
          "title": "No",
          "price": 0.8975
        }
      ],
      "volume": 61493956.24918217,
      "liquidity": 7339095.12131,
      "lastUpdated": "2026-06-28T20:19:38.305Z"
    },
    {
      "id": "558936",
      "question": "Will France win the 2026 FIFA World Cup?",
      "category": "General",
      "endDate": "2026-07-20T00:00:00Z",
      "yesPrice": 0.2295,
      "outcomes": [
        {
          "id": "558936-0",
          "title": "Yes",
          "price": 0.2295
        },
        {
          "id": "558936-1",
          "title": "No",
          "price": 0.7705
        }
      ],
      "volume": 77726031.94241299,
      "liquidity": 7320426.11182,
      "lastUpdated": "2026-06-28T20:19:38.305Z"
    },
    {
      "id": "2682268",
      "question": "South Africa vs. Canada: Team to Advance",
      "category": "General",
      "endDate": "2026-06-28T19:00:00Z",
      "yesPrice": 0.335,
      "outcomes": [
        {
          "id": "2682268-0",
          "title": "South Africa",
          "price": 0.335
        },
        {
          "id": "2682268-1",
          "title": "Canada",
          "price": 0.665
        }
      ],
      "volume": 2041560.1392840012,
      "liquidity": 212694.7466,
      "lastUpdated": "2026-06-28T20:19:38.305Z"
    },
    {
      "id": "2680427",
      "question": "South Africa vs. Canada: O/U 2.5",
      "category": "General",
      "endDate": "2026-06-28T19:00:00Z",
      "yesPrice": 0.095,
      "outcomes": [
        {
          "id": "2680427-0",
          "title": "Over",
          "price": 0.095
        },
        {
          "id": "2680427-1",
          "title": "Under",
          "price": 0.905
        }
      ],
      "volume": 1417890.076370994,
      "liquidity": 189793.5403,
      "lastUpdated": "2026-06-28T20:19:38.305Z"
    },
    {
      "id": "2680416",
      "question": "Spread: Canada (-1.5)",
      "category": "General",
      "endDate": "2026-06-28T19:00:00Z",
      "yesPrice": 0.115,
      "outcomes": [
        {
          "id": "2680416-0",
          "title": "Canada",
          "price": 0.115
        },
        {
          "id": "2680416-1",
          "title": "South Africa",
          "price": 0.885
        }
      ],
      "volume": 1295790.640839005,
      "liquidity": 261654.3854,
      "lastUpdated": "2026-06-28T20:19:38.305Z"
    },
    {
      "id": "2690979",
      "question": "Will Brazil win on 2026-06-29?",
      "category": "General",
      "endDate": "2026-06-29T17:00:00Z",
      "yesPrice": 0.575,
      "outcomes": [
        {
          "id": "2690979-0",
          "title": "Yes",
          "price": 0.575
        },
        {
          "id": "2690979-1",
          "title": "No",
          "price": 0.425
        }
      ],
      "volume": 1439126.9260080103,
      "liquidity": 1650429.1715,
      "lastUpdated": "2026-06-28T20:19:38.305Z"
    },
    {
      "id": "2690992",
      "question": "Will Netherlands win on 2026-06-29?",
      "category": "General",
      "endDate": "2026-06-30T01:00:00Z",
      "yesPrice": 0.435,
      "outcomes": [
        {
          "id": "2690992-0",
          "title": "Yes",
          "price": 0.435
        },
        {
          "id": "2690992-1",
          "title": "No",
          "price": 0.565
        }
      ],
      "volume": 928725.7724330081,
      "liquidity": 779391.905,
      "lastUpdated": "2026-06-28T20:19:38.305Z"
    },
    {
      "id": "2680434",
      "question": "South Africa vs. Canada: Both Teams to Score",
      "category": "General",
      "endDate": "2026-06-28T19:00:00Z",
      "yesPrice": 0.175,
      "outcomes": [
        {
          "id": "2680434-0",
          "title": "Yes",
          "price": 0.175
        },
        {
          "id": "2680434-1",
          "title": "No",
          "price": 0.825
        }
      ],
      "volume": 607017.4270429978,
      "liquidity": 106812.7961,
      "lastUpdated": "2026-06-28T20:19:38.305Z"
    },
    {
      "id": "2707644",
      "question": "Will France win on 2026-06-30?",
      "category": "General",
      "endDate": "2026-06-30T21:00:00Z",
      "yesPrice": 0.775,
      "outcomes": [
        {
          "id": "2707644-0",
          "title": "Yes",
          "price": 0.775
        },
        {
          "id": "2707644-1",
          "title": "No",
          "price": 0.225
        }
      ],
      "volume": 637046.3182190049,
      "liquidity": 780899.7747,
      "lastUpdated": "2026-06-28T20:19:38.305Z"
    },
    {
      "id": "2707623",
      "question": "Will Germany win on 2026-06-29?",
      "category": "General",
      "endDate": "2026-06-29T20:30:00Z",
      "yesPrice": 0.735,
      "outcomes": [
        {
          "id": "2707623-0",
          "title": "Yes",
          "price": 0.735
        },
        {
          "id": "2707623-1",
          "title": "No",
          "price": 0.265
        }
      ],
      "volume": 577746.3139419997,
      "liquidity": 1319042.7076,
      "lastUpdated": "2026-06-28T20:19:38.305Z"
    },
    {
      "id": "2680426",
      "question": "South Africa vs. Canada: O/U 1.5",
      "category": "General",
      "endDate": "2026-06-28T19:00:00Z",
      "yesPrice": 0.305,
      "outcomes": [
        {
          "id": "2680426-0",
          "title": "Over",
          "price": 0.305
        },
        {
          "id": "2680426-1",
          "title": "Under",
          "price": 0.695
        }
      ],
      "volume": 554949.3436760003,
      "liquidity": 108632.141,
      "lastUpdated": "2026-06-28T20:19:38.305Z"
    },
    {
      "id": "2639023",
      "question": "Houston Astros vs. Detroit Tigers",
      "category": "General",
      "endDate": "2026-07-05T17:40:00Z",
      "yesPrice": 0.445,
      "outcomes": [
        {
          "id": "2639023-0",
          "title": "Houston Astros",
          "price": 0.445
        },
        {
          "id": "2639023-1",
          "title": "Detroit Tigers",
          "price": 0.555
        }
      ],
      "volume": 507938.79436000035,
      "liquidity": 64304.3076,
      "lastUpdated": "2026-06-28T20:19:38.305Z"
    },
    {
      "id": "560317",
      "question": "Putin out as President of Russia by December 31, 2026?",
      "category": "General",
      "endDate": "2026-12-31T18:30:00Z",
      "yesPrice": 0.115,
      "outcomes": [
        {
          "id": "560317-0",
          "title": "Yes",
          "price": 0.115
        },
        {
          "id": "560317-1",
          "title": "No",
          "price": 0.885
        }
      ],
      "volume": 10101593.984913018,
      "liquidity": 584321.2691,
      "lastUpdated": "2026-06-28T20:19:38.305Z"
    },
    {
      "id": "2690981",
      "question": "Will Brazil vs. Japan end in a draw?",
      "category": "General",
      "endDate": "2026-06-29T17:00:00Z",
      "yesPrice": 0.255,
      "outcomes": [
        {
          "id": "2690981-0",
          "title": "Yes",
          "price": 0.255
        },
        {
          "id": "2690981-1",
          "title": "No",
          "price": 0.745
        }
      ],
      "volume": 670713.8671400081,
      "liquidity": 2076113.2718,
      "lastUpdated": "2026-06-28T20:19:38.305Z"
    },
    {
      "id": "2680306",
      "question": "Exact Score: South Africa 1 - 2 Canada?",
      "category": "General",
      "endDate": "2026-06-28T19:00:00Z",
      "yesPrice": 0.035,
      "outcomes": [
        {
          "id": "2680306-0",
          "title": "Yes",
          "price": 0.035
        },
        {
          "id": "2680306-1",
          "title": "No",
          "price": 0.965
        }
      ],
      "volume": 450099.89339000173,
      "liquidity": 39121.527,
      "lastUpdated": "2026-06-28T20:19:38.305Z"
    },
    {
      "id": "2639019",
      "question": "Texas Rangers vs. Toronto Blue Jays",
      "category": "General",
      "endDate": "2026-07-05T17:37:00Z",
      "yesPrice": 0.485,
      "outcomes": [
        {
          "id": "2639019-0",
          "title": "Texas Rangers",
          "price": 0.485
        },
        {
          "id": "2639019-1",
          "title": "Toronto Blue Jays",
          "price": 0.515
        }
      ],
      "volume": 412814.88538600056,
      "liquidity": 60857.9539,
      "lastUpdated": "2026-06-28T20:19:38.305Z"
    },
    {
      "id": "2690983",
      "question": "Will Japan win on 2026-06-29?",
      "category": "General",
      "endDate": "2026-06-29T17:00:00Z",
      "yesPrice": 0.185,
      "outcomes": [
        {
          "id": "2690983-0",
          "title": "Yes",
          "price": 0.185
        },
        {
          "id": "2690983-1",
          "title": "No",
          "price": 0.815
        }
      ],
      "volume": 674944.5720720005,
      "liquidity": 2233372.8918,
      "lastUpdated": "2026-06-28T20:19:38.305Z"
    },
    {
      "id": "2696188",
      "question": "Brazil vs. Japan: O/U 2.5",
      "category": "General",
      "endDate": "2026-06-29T17:00:00Z",
      "yesPrice": 0.445,
      "outcomes": [
        {
          "id": "2696188-0",
          "title": "Over",
          "price": 0.445
        },
        {
          "id": "2696188-1",
          "title": "Under",
          "price": 0.555
        }
      ],
      "volume": 393578.15467499977,
      "liquidity": 363392.9153,
      "lastUpdated": "2026-06-28T20:19:38.305Z"
    },
    {
      "id": "703257",
      "question": "Will the US confirm that aliens exist before 2027?",
      "category": "General",
      "endDate": "2026-12-31T00:00:00Z",
      "yesPrice": 0.085,
      "outcomes": [
        {
          "id": "703257-0",
          "title": "Yes",
          "price": 0.085
        },
        {
          "id": "703257-1",
          "title": "No",
          "price": 0.915
        }
      ],
      "volume": 34884051.98325351,
      "liquidity": 677759.2579,
      "lastUpdated": "2026-06-28T20:19:38.305Z"
    },
    {
      "id": "2176262",
      "question": "Strait of Hormuz traffic returns to normal by July 31?",
      "category": "General",
      "endDate": "2026-07-31T00:00:00Z",
      "yesPrice": 0.335,
      "outcomes": [
        {
          "id": "2176262-0",
          "title": "Yes",
          "price": 0.335
        },
        {
          "id": "2176262-1",
          "title": "No",
          "price": 0.665
        }
      ],
      "volume": 10522471.196805144,
      "liquidity": 368703.5965,
      "lastUpdated": "2026-06-28T20:19:38.305Z"
    },
    {
      "id": "2680297",
      "question": "Exact Score: South Africa 0 - 0 Canada?",
      "category": "General",
      "endDate": "2026-06-28T19:00:00Z",
      "yesPrice": 0.345,
      "outcomes": [
        {
          "id": "2680297-0",
          "title": "Yes",
          "price": 0.345
        },
        {
          "id": "2680297-1",
          "title": "No",
          "price": 0.655
        }
      ],
      "volume": 332590.3040579999,
      "liquidity": 91709.29,
      "lastUpdated": "2026-06-28T20:19:38.305Z"
    },
    {
      "id": "2639031",
      "question": "Chicago Cubs vs. Milwaukee Brewers",
      "category": "General",
      "endDate": "2026-07-05T18:10:00Z",
      "yesPrice": 0.415,
      "outcomes": [
        {
          "id": "2639031-0",
          "title": "Chicago Cubs",
          "price": 0.415
        },
        {
          "id": "2639031-1",
          "title": "Milwaukee Brewers",
          "price": 0.585
        }
      ],
      "volume": 322667.26037100016,
      "liquidity": 21308.7487,
      "lastUpdated": "2026-06-28T20:19:38.305Z"
    },
    {
      "id": "2639037",
      "question": "Athletics vs. Los Angeles Angels",
      "category": "General",
      "endDate": "2026-07-05T19:15:00Z",
      "yesPrice": 0.105,
      "outcomes": [
        {
          "id": "2639037-0",
          "title": "Athletics",
          "price": 0.105
        },
        {
          "id": "2639037-1",
          "title": "Los Angeles Angels",
          "price": 0.895
        }
      ],
      "volume": 303454.85488399677,
      "liquidity": 16123.7725,
      "lastUpdated": "2026-06-28T20:19:38.305Z"
    },
    {
      "id": "2680443",
      "question": "South Africa vs. Canada: Canada O/U 1.5",
      "category": "General",
      "endDate": "2026-06-28T19:00:00Z",
      "yesPrice": 0.155,
      "outcomes": [
        {
          "id": "2680443-0",
          "title": "Over",
          "price": 0.155
        },
        {
          "id": "2680443-1",
          "title": "Under",
          "price": 0.845
        }
      ],
      "volume": 302871.2409270003,
      "liquidity": 117148.6689,
      "lastUpdated": "2026-06-28T20:19:38.305Z"
    },
    {
      "id": "2692616",
      "question": "South Africa vs. Canada: O/U 8.5 Total Corners",
      "category": "General",
      "endDate": "2026-06-28T19:00:00Z",
      "yesPrice": 0.46,
      "outcomes": [
        {
          "id": "2692616-0",
          "title": "Over",
          "price": 0.46
        },
        {
          "id": "2692616-1",
          "title": "Under",
          "price": 0.54
        }
      ],
      "volume": 302078.8056179998,
      "liquidity": 13600.1731,
      "lastUpdated": "2026-06-28T20:19:38.305Z"
    },
    {
      "id": "2680425",
      "question": "South Africa vs. Canada: O/U 0.5",
      "category": "General",
      "endDate": "2026-06-28T19:00:00Z",
      "yesPrice": 0.655,
      "outcomes": [
        {
          "id": "2680425-0",
          "title": "Over",
          "price": 0.655
        },
        {
          "id": "2680425-1",
          "title": "Under",
          "price": 0.345
        }
      ],
      "volume": 301338.5174060002,
      "liquidity": 166003.1889,
      "lastUpdated": "2026-06-28T20:19:38.305Z"
    },
    {
      "id": "693485",
      "question": "Will Lebanon recognize Israel by June 30?",
      "category": "General",
      "endDate": null,
      "yesPrice": 0.661,
      "outcomes": [
        {
          "id": "693485-0",
          "title": "Yes",
          "price": 0.661
        },
        {
          "id": "693485-1",
          "title": "No",
          "price": 0.339
        }
      ],
      "volume": 384423.36227000057,
      "liquidity": 52760.98725,
      "lastUpdated": "2026-06-28T20:19:38.305Z"
    },
    {
      "id": "2639033",
      "question": "Colorado Rockies vs. Minnesota Twins",
      "category": "General",
      "endDate": "2026-07-05T18:10:00Z",
      "yesPrice": 0.165,
      "outcomes": [
        {
          "id": "2639033-0",
          "title": "Colorado Rockies",
          "price": 0.165
        },
        {
          "id": "2639033-1",
          "title": "Minnesota Twins",
          "price": 0.835
        }
      ],
      "volume": 291621.28820100025,
      "liquidity": 43121.8955,
      "lastUpdated": "2026-06-28T20:19:38.305Z"
    },
    {
      "id": "2680303",
      "question": "Exact Score: South Africa 1 - 1 Canada?",
      "category": "General",
      "endDate": "2026-06-28T19:00:00Z",
      "yesPrice": 0.11,
      "outcomes": [
        {
          "id": "2680303-0",
          "title": "Yes",
          "price": 0.11
        },
        {
          "id": "2680303-1",
          "title": "No",
          "price": 0.89
        }
      ],
      "volume": 286807.44768199563,
      "liquidity": 51275.824,
      "lastUpdated": "2026-06-28T20:19:38.305Z"
    },
    {
      "id": "2680301",
      "question": "Exact Score: South Africa 0 - 2 Canada?",
      "category": "General",
      "endDate": "2026-06-28T19:00:00Z",
      "yesPrice": 0.085,
      "outcomes": [
        {
          "id": "2680301-0",
          "title": "Yes",
          "price": 0.085
        },
        {
          "id": "2680301-1",
          "title": "No",
          "price": 0.915
        }
      ],
      "volume": 296865.50590200076,
      "liquidity": 37884.3255,
      "lastUpdated": "2026-06-28T20:19:38.305Z"
    },
    {
      "id": "2692617",
      "question": "South Africa vs. Canada: O/U 9.5 Total Corners",
      "category": "General",
      "endDate": "2026-06-28T19:00:00Z",
      "yesPrice": 0.34,
      "outcomes": [
        {
          "id": "2692617-0",
          "title": "Over",
          "price": 0.34
        },
        {
          "id": "2692617-1",
          "title": "Under",
          "price": 0.66
        }
      ],
      "volume": 285409.9155849996,
      "liquidity": 4836.1349,
      "lastUpdated": "2026-06-28T20:19:38.305Z"
    },
    {
      "id": "2707639",
      "question": "Will Norway win on 2026-06-30?",
      "category": "General",
      "endDate": "2026-06-30T17:00:00Z",
      "yesPrice": 0.475,
      "outcomes": [
        {
          "id": "2707639-0",
          "title": "Yes",
          "price": 0.475
        },
        {
          "id": "2707639-1",
          "title": "No",
          "price": 0.525
        }
      ],
      "volume": 454998.13513301616,
      "liquidity": 536107.7116,
      "lastUpdated": "2026-06-28T20:19:38.305Z"
    },
    {
      "id": "572133",
      "question": "No one announced as next James Bond?",
      "category": "General",
      "endDate": "2026-06-30T00:00:00Z",
      "yesPrice": 0.9665,
      "outcomes": [
        {
          "id": "572133-0",
          "title": "Yes",
          "price": 0.9665
        },
        {
          "id": "572133-1",
          "title": "No",
          "price": 0.0335
        }
      ],
      "volume": 655275.5288760002,
      "liquidity": 85044.2628,
      "lastUpdated": "2026-06-28T20:19:38.305Z"
    },
    {
      "id": "2711267",
      "question": "Texas Rangers vs. Toronto Blue Jays: O/U 8.5",
      "category": "General",
      "endDate": "2026-06-28T17:37:00Z",
      "yesPrice": 0.13,
      "outcomes": [
        {
          "id": "2711267-0",
          "title": "Over",
          "price": 0.13
        },
        {
          "id": "2711267-1",
          "title": "Under",
          "price": 0.87
        }
      ],
      "volume": 264134.44791600003,
      "liquidity": 3310.57846,
      "lastUpdated": "2026-06-28T20:19:38.305Z"
    },
    {
      "id": "2639029",
      "question": "Kansas City Royals vs. Chicago White Sox",
      "category": "General",
      "endDate": "2026-07-05T18:10:00Z",
      "yesPrice": 0.595,
      "outcomes": [
        {
          "id": "2639029-0",
          "title": "Kansas City Royals",
          "price": 0.595
        },
        {
          "id": "2639029-1",
          "title": "Chicago White Sox",
          "price": 0.405
        }
      ],
      "volume": 260668.29704499984,
      "liquidity": 76610.4208,
      "lastUpdated": "2026-06-28T20:19:38.305Z"
    },
    {
      "id": "2639015",
      "question": "Washington Nationals vs. Baltimore Orioles",
      "category": "General",
      "endDate": "2026-07-05T17:35:00Z",
      "yesPrice": 0.795,
      "outcomes": [
        {
          "id": "2639015-0",
          "title": "Washington Nationals",
          "price": 0.795
        },
        {
          "id": "2639015-1",
          "title": "Baltimore Orioles",
          "price": 0.205
        }
      ],
      "volume": 254620.4908370001,
      "liquidity": 78574.3498,
      "lastUpdated": "2026-06-28T20:19:38.305Z"
    },
    {
      "id": "2711282",
      "question": "Seattle Mariners vs. Cleveland Guardians: O/U 7.5",
      "category": "General",
      "endDate": "2026-06-28T17:40:00Z",
      "yesPrice": 0.29,
      "outcomes": [
        {
          "id": "2711282-0",
          "title": "Over",
          "price": 0.29
        },
        {
          "id": "2711282-1",
          "title": "Under",
          "price": 0.71
        }
      ],
      "volume": 245239.26493100013,
      "liquidity": 36764.0783,
      "lastUpdated": "2026-06-28T20:19:38.305Z"
    },
    {
      "id": "2680299",
      "question": "Exact Score: South Africa 0 - 1 Canada?",
      "category": "General",
      "endDate": "2026-06-28T19:00:00Z",
      "yesPrice": 0.23,
      "outcomes": [
        {
          "id": "2680299-0",
          "title": "Yes",
          "price": 0.23
        },
        {
          "id": "2680299-1",
          "title": "No",
          "price": 0.77
        }
      ],
      "volume": 254063.20427399757,
      "liquidity": 43625.0176,
      "lastUpdated": "2026-06-28T20:19:38.305Z"
    },
    {
      "id": "2707658",
      "question": "Will Argentina win on 2026-07-03?",
      "category": "General",
      "endDate": "2026-07-03T22:00:00Z",
      "yesPrice": 0.855,
      "outcomes": [
        {
          "id": "2707658-0",
          "title": "Yes",
          "price": 0.855
        },
        {
          "id": "2707658-1",
          "title": "No",
          "price": 0.145
        }
      ],
      "volume": 260865.1747200017,
      "liquidity": 246042.0765,
      "lastUpdated": "2026-06-28T20:19:38.305Z"
    },
    {
      "id": "2708026",
      "question": "Spread: Germany (-1.5)",
      "category": "General",
      "endDate": "2026-06-29T20:30:00Z",
      "yesPrice": 0.485,
      "outcomes": [
        {
          "id": "2708026-0",
          "title": "Germany",
          "price": 0.485
        },
        {
          "id": "2708026-1",
          "title": "Paraguay",
          "price": 0.515
        }
      ],
      "volume": 233330.34547099992,
      "liquidity": 366166.6441,
      "lastUpdated": "2026-06-28T20:19:38.305Z"
    },
    {
      "id": "2535468",
      "question": "Strait of Hormuz traffic returns to normal by July 15?",
      "category": "General",
      "endDate": "2026-07-15T00:00:00Z",
      "yesPrice": 0.135,
      "outcomes": [
        {
          "id": "2535468-0",
          "title": "Yes",
          "price": 0.135
        },
        {
          "id": "2535468-1",
          "title": "No",
          "price": 0.865
        }
      ],
      "volume": 4752866.577544947,
      "liquidity": 174586.7017,
      "lastUpdated": "2026-06-28T20:19:38.305Z"
    },
    {
      "id": "2639017",
      "question": "Cincinnati Reds vs. Pittsburgh Pirates",
      "category": "General",
      "endDate": "2026-07-05T17:35:00Z",
      "yesPrice": 0.135,
      "outcomes": [
        {
          "id": "2639017-0",
          "title": "Cincinnati Reds",
          "price": 0.135
        },
        {
          "id": "2639017-1",
          "title": "Pittsburgh Pirates",
          "price": 0.865
        }
      ],
      "volume": 241354.8449879999,
      "liquidity": 50921.5326,
      "lastUpdated": "2026-06-28T20:19:38.305Z"
    },
    {
      "id": "2639025",
      "question": "Philadelphia Phillies vs. New York Mets",
      "category": "General",
      "endDate": "2026-07-05T17:40:00Z",
      "yesPrice": 0.695,
      "outcomes": [
        {
          "id": "2639025-0",
          "title": "Philadelphia Phillies",
          "price": 0.695
        },
        {
          "id": "2639025-1",
          "title": "New York Mets",
          "price": 0.305
        }
      ],
      "volume": 235014.0410139993,
      "liquidity": 46709.876,
      "lastUpdated": "2026-06-28T20:19:38.305Z"
    },
    {
      "id": "2714114",
      "question": "Counter-Strike: Inner Circle Esports vs Acend (BO5) - Super DraculaN Playoffs",
      "category": "General",
      "endDate": "2026-06-28T23:30:00Z",
      "yesPrice": 0.62,
      "outcomes": [
        {
          "id": "2714114-0",
          "title": "Inner Circle Esports",
          "price": 0.62
        },
        {
          "id": "2714114-1",
          "title": "Acend",
          "price": 0.38
        }
      ],
      "volume": 211668.18425300045,
      "liquidity": 28220.8635,
      "lastUpdated": "2026-06-28T20:19:38.305Z"
    },
    {
      "id": "2690999",
      "question": "Will United States win on 2026-07-01?",
      "category": "General",
      "endDate": "2026-07-02T00:00:00Z",
      "yesPrice": 0.715,
      "outcomes": [
        {
          "id": "2690999-0",
          "title": "Yes",
          "price": 0.715
        },
        {
          "id": "2690999-1",
          "title": "No",
          "price": 0.285
        }
      ],
      "volume": 272246.5413820002,
      "liquidity": 413002.5981,
      "lastUpdated": "2026-06-28T20:19:38.305Z"
    }
  ],
  "lastUpdated": "2026-06-28T20:19:39.014Z"
}