{
  "markets": [
    {
      "id": "558938",
      "question": "Will Argentina win the 2026 FIFA World Cup?",
      "category": "General",
      "endDate": "2026-07-20T00:00:00Z",
      "yesPrice": 0.4195,
      "outcomes": [
        {
          "id": "558938-0",
          "title": "Yes",
          "price": 0.4195
        },
        {
          "id": "558938-1",
          "title": "No",
          "price": 0.5805
        }
      ],
      "volume": 151446769.17831364,
      "liquidity": 7388410.0859,
      "lastUpdated": "2026-07-16T03:41:25.650Z"
    },
    {
      "id": "558934",
      "question": "Will Spain win the 2026 FIFA World Cup?",
      "category": "General",
      "endDate": "2026-07-20T00:00:00Z",
      "yesPrice": 0.5795,
      "outcomes": [
        {
          "id": "558934-0",
          "title": "Yes",
          "price": 0.5795
        },
        {
          "id": "558934-1",
          "title": "No",
          "price": 0.4205
        }
      ],
      "volume": 120561762.61566092,
      "liquidity": 6531224.18757,
      "lastUpdated": "2026-07-16T03:41:25.650Z"
    },
    {
      "id": "2069635",
      "question": "Will Lionel Messi be the top goalscorer at the 2026 FIFA World Cup?",
      "category": "General",
      "endDate": "2026-07-20T00:00:00Z",
      "yesPrice": 0.6435,
      "outcomes": [
        {
          "id": "2069635-0",
          "title": "Yes",
          "price": 0.6435
        },
        {
          "id": "2069635-1",
          "title": "No",
          "price": 0.3565
        }
      ],
      "volume": 4934969.440507962,
      "liquidity": 693382.4189,
      "lastUpdated": "2026-07-16T03:41:25.650Z"
    },
    {
      "id": "665374",
      "question": "Will the U.S. invade Iran before 2027?",
      "category": "General",
      "endDate": "2026-12-31T00:00:00Z",
      "yesPrice": 0.235,
      "outcomes": [
        {
          "id": "665374-0",
          "title": "Yes",
          "price": 0.235
        },
        {
          "id": "665374-1",
          "title": "No",
          "price": 0.765
        }
      ],
      "volume": 42974894.91582512,
      "liquidity": 566059.6021,
      "lastUpdated": "2026-07-16T03:41:25.650Z"
    },
    {
      "id": "1654958",
      "question": "Will there be no change in Fed interest rates after the July 2026 meeting?",
      "category": "General",
      "endDate": "2026-07-29T00:00:00Z",
      "yesPrice": 0.9565,
      "outcomes": [
        {
          "id": "1654958-0",
          "title": "Yes",
          "price": 0.9565
        },
        {
          "id": "1654958-1",
          "title": "No",
          "price": 0.0435
        }
      ],
      "volume": 19061272.96047408,
      "liquidity": 537627.93571,
      "lastUpdated": "2026-07-16T03:41:25.650Z"
    },
    {
      "id": "2069638",
      "question": "Will Kylian Mbappe be the top goalscorer at the 2026 FIFA World Cup?",
      "category": "General",
      "endDate": "2026-07-20T00:00:00Z",
      "yesPrice": 0.345,
      "outcomes": [
        {
          "id": "2069638-0",
          "title": "Yes",
          "price": 0.345
        },
        {
          "id": "2069638-1",
          "title": "No",
          "price": 0.655
        }
      ],
      "volume": 4884995.273410893,
      "liquidity": 536417.3703,
      "lastUpdated": "2026-07-16T03:41:25.650Z"
    },
    {
      "id": "1654959",
      "question": "Will the Fed increase interest rates by 25 bps after the July 2026 meeting?",
      "category": "General",
      "endDate": "2026-07-29T00:00:00Z",
      "yesPrice": 0.0375,
      "outcomes": [
        {
          "id": "1654959-0",
          "title": "Yes",
          "price": 0.0375
        },
        {
          "id": "1654959-1",
          "title": "No",
          "price": 0.9625
        }
      ],
      "volume": 13957362.691909174,
      "liquidity": 473053.15885,
      "lastUpdated": "2026-07-16T03:41:25.650Z"
    },
    {
      "id": "2923086",
      "question": "Swiss Open: Jerome Kym vs Stefanos Tsitsipas",
      "category": "General",
      "endDate": "2026-07-22T08:00:00Z",
      "yesPrice": 0.3765,
      "outcomes": [
        {
          "id": "2923086-0",
          "title": "Jerome Kym",
          "price": 0.3765
        },
        {
          "id": "2923086-1",
          "title": "Stefanos Tsitsipas",
          "price": 0.6235
        }
      ],
      "volume": 512716.7104190006,
      "liquidity": 12964.46468,
      "lastUpdated": "2026-07-16T03:41:25.650Z"
    },
    {
      "id": "2853044",
      "question": "Will Iran announce withdrawal from MOU negotiations by July 17?",
      "category": "General",
      "endDate": "2026-07-17T23:59:00Z",
      "yesPrice": 0.05,
      "outcomes": [
        {
          "id": "2853044-0",
          "title": "Yes",
          "price": 0.05
        },
        {
          "id": "2853044-1",
          "title": "No",
          "price": 0.95
        }
      ],
      "volume": 1094413.9412569976,
      "liquidity": 139039.87959,
      "lastUpdated": "2026-07-16T03:41:25.650Z"
    },
    {
      "id": "2507618",
      "question": "Kharg Island no longer under Iranian control by August 31?",
      "category": "General",
      "endDate": "2026-06-30T23:55:00Z",
      "yesPrice": 0.0825,
      "outcomes": [
        {
          "id": "2507618-0",
          "title": "Yes",
          "price": 0.0825
        },
        {
          "id": "2507618-1",
          "title": "No",
          "price": 0.9175
        }
      ],
      "volume": 1570944.9962470022,
      "liquidity": 103932.75478,
      "lastUpdated": "2026-07-16T03:41:25.650Z"
    },
    {
      "id": "2934008",
      "question": "LoL: Bilibili Gaming vs T1 (BO1) - Esports World Cup Group C",
      "category": "General",
      "endDate": "2026-07-16T15:00:00Z",
      "yesPrice": 0.575,
      "outcomes": [
        {
          "id": "2934008-0",
          "title": "Bilibili Gaming",
          "price": 0.575
        },
        {
          "id": "2934008-1",
          "title": "T1",
          "price": 0.425
        }
      ],
      "volume": 232661.66132400004,
      "liquidity": 261617.5045,
      "lastUpdated": "2026-07-16T03:41:25.650Z"
    },
    {
      "id": "2431013",
      "question": "Will Lionel Messi win the Golden Ball at the 2026 FIFA World Cup?",
      "category": "General",
      "endDate": "2026-07-20T03:59:00Z",
      "yesPrice": 0.909,
      "outcomes": [
        {
          "id": "2431013-0",
          "title": "Yes",
          "price": 0.909
        },
        {
          "id": "2431013-1",
          "title": "No",
          "price": 0.091
        }
      ],
      "volume": 585564.935699001,
      "liquidity": 263093.88876,
      "lastUpdated": "2026-07-16T03:41:25.650Z"
    },
    {
      "id": "2643400",
      "question": "Will Iran announce withdrawal from MOU negotiations by July 31?",
      "category": "General",
      "endDate": "2026-07-31T23:59:00Z",
      "yesPrice": 0.155,
      "outcomes": [
        {
          "id": "2643400-0",
          "title": "Yes",
          "price": 0.155
        },
        {
          "id": "2643400-1",
          "title": "No",
          "price": 0.845
        }
      ],
      "volume": 2034184.410769002,
      "liquidity": 92742.0163,
      "lastUpdated": "2026-07-16T03:41:25.650Z"
    },
    {
      "id": "840929",
      "question": "Will Europe (UEFA) win the 2026 FIFA World Cup?",
      "category": "General",
      "endDate": null,
      "yesPrice": 0.585,
      "outcomes": [
        {
          "id": "840929-0",
          "title": "Yes",
          "price": 0.585
        },
        {
          "id": "840929-1",
          "title": "No",
          "price": 0.415
        }
      ],
      "volume": 1647232.1006589965,
      "liquidity": 1838210.9617,
      "lastUpdated": "2026-07-16T03:41:25.650Z"
    },
    {
      "id": "1931108",
      "question": "Will LeBron James play for the Golden State Warriors in 2026-27?",
      "category": "General",
      "endDate": "2026-10-31T03:59:00Z",
      "yesPrice": 0.2935,
      "outcomes": [
        {
          "id": "1931108-0",
          "title": "Yes",
          "price": 0.2935
        },
        {
          "id": "1931108-1",
          "title": "No",
          "price": 0.7065
        }
      ],
      "volume": 1894382.160469996,
      "liquidity": 40603.70167,
      "lastUpdated": "2026-07-16T03:41:25.650Z"
    },
    {
      "id": "2775250",
      "question": "Will the Detroit Tigers have the highest ABS success rate during the 2026 MLB regular season?",
      "category": "General",
      "endDate": "2026-10-11T23:59:00Z",
      "yesPrice": 0.156,
      "outcomes": [
        {
          "id": "2775250-0",
          "title": "Yes",
          "price": 0.156
        },
        {
          "id": "2775250-1",
          "title": "No",
          "price": 0.844
        }
      ],
      "volume": 152185.3,
      "liquidity": 186.4448,
      "lastUpdated": "2026-07-16T03:41:25.650Z"
    },
    {
      "id": "567621",
      "question": "Will China invade Taiwan by end of 2026?",
      "category": "General",
      "endDate": "2026-12-31T00:00:00Z",
      "yesPrice": 0.0385,
      "outcomes": [
        {
          "id": "567621-0",
          "title": "Yes",
          "price": 0.0385
        },
        {
          "id": "567621-1",
          "title": "No",
          "price": 0.9615
        }
      ],
      "volume": 38565604.81317929,
      "liquidity": 692805.97138,
      "lastUpdated": "2026-07-16T03:41:25.650Z"
    },
    {
      "id": "1931104",
      "question": "Will LeBron James play for the Cleveland Cavaliers in 2026-27?",
      "category": "General",
      "endDate": "2026-10-31T03:59:00Z",
      "yesPrice": 0.3925,
      "outcomes": [
        {
          "id": "1931104-0",
          "title": "Yes",
          "price": 0.3925
        },
        {
          "id": "1931104-1",
          "title": "No",
          "price": 0.6075
        }
      ],
      "volume": 2286249.118440998,
      "liquidity": 56005.05237,
      "lastUpdated": "2026-07-16T03:41:25.650Z"
    },
    {
      "id": "2845812",
      "question": "Over $30M committed to the Credible public sale?",
      "category": "General",
      "endDate": "2026-08-31T23:59:00Z",
      "yesPrice": 0.905,
      "outcomes": [
        {
          "id": "2845812-0",
          "title": "Yes",
          "price": 0.905
        },
        {
          "id": "2845812-1",
          "title": "No",
          "price": 0.095
        }
      ],
      "volume": 219632.04357499996,
      "liquidity": 49858.061,
      "lastUpdated": "2026-07-16T03:41:25.650Z"
    },
    {
      "id": "2758339",
      "question": "Will Bitcoin reach $67,500 in July?",
      "category": "General",
      "endDate": "2026-08-01T04:00:00Z",
      "yesPrice": 0.515,
      "outcomes": [
        {
          "id": "2758339-0",
          "title": "Yes",
          "price": 0.515
        },
        {
          "id": "2758339-1",
          "title": "No",
          "price": 0.485
        }
      ],
      "volume": 1084723.1309119985,
      "liquidity": 37733.6401,
      "lastUpdated": "2026-07-16T03:41:25.650Z"
    },
    {
      "id": "2730117",
      "question": "Will WTI Crude Oil (WTI) hit (HIGH) $95 in July?",
      "category": "General",
      "endDate": "2026-08-01T03:59:59.999Z",
      "yesPrice": 0.128,
      "outcomes": [
        {
          "id": "2730117-0",
          "title": "Yes",
          "price": 0.128
        },
        {
          "id": "2730117-1",
          "title": "No",
          "price": 0.872
        }
      ],
      "volume": 608609.876579,
      "liquidity": 42100.38723,
      "lastUpdated": "2026-07-16T03:41:25.650Z"
    },
    {
      "id": "1163699",
      "question": "Clarity Act signed into law in 2026?",
      "category": "General",
      "endDate": "2027-01-01T05:00:00Z",
      "yesPrice": 0.395,
      "outcomes": [
        {
          "id": "1163699-0",
          "title": "Yes",
          "price": 0.395
        },
        {
          "id": "1163699-1",
          "title": "No",
          "price": 0.605
        }
      ],
      "volume": 1815491.0529779946,
      "liquidity": 38892.8245,
      "lastUpdated": "2026-07-16T03:41:25.650Z"
    },
    {
      "id": "677408",
      "question": "China x Philippines military clash before 2027?",
      "category": "General",
      "endDate": "2026-12-31T00:00:00Z",
      "yesPrice": 0.105,
      "outcomes": [
        {
          "id": "677408-0",
          "title": "Yes",
          "price": 0.105
        },
        {
          "id": "677408-1",
          "title": "No",
          "price": 0.895
        }
      ],
      "volume": 1522104.1837789945,
      "liquidity": 50097.8798,
      "lastUpdated": "2026-07-16T03:41:25.650Z"
    },
    {
      "id": "2825502",
      "question": "Will Elon Musk post 120-139 tweets from July 10 to July 17, 2026?",
      "category": "General",
      "endDate": "2026-07-17T16:00:00Z",
      "yesPrice": 0.1435,
      "outcomes": [
        {
          "id": "2825502-0",
          "title": "Yes",
          "price": 0.1435
        },
        {
          "id": "2825502-1",
          "title": "No",
          "price": 0.8565
        }
      ],
      "volume": 193154.65916299992,
      "liquidity": 24608.00994,
      "lastUpdated": "2026-07-16T03:41:25.650Z"
    },
    {
      "id": "2933207",
      "question": "LoL: Sentinels vs Gen.G (BO1) - Esports World Cup Group B",
      "category": "General",
      "endDate": "2026-07-16T15:00:00Z",
      "yesPrice": 0.065,
      "outcomes": [
        {
          "id": "2933207-0",
          "title": "Sentinels",
          "price": 0.065
        },
        {
          "id": "2933207-1",
          "title": "Gen.G",
          "price": 0.935
        }
      ],
      "volume": 106303.06226000005,
      "liquidity": 234807.2687,
      "lastUpdated": "2026-07-16T03:41:25.650Z"
    },
    {
      "id": "840931",
      "question": "Will South America (CONMEBOL) win the 2026 FIFA World Cup?",
      "category": "General",
      "endDate": null,
      "yesPrice": 0.415,
      "outcomes": [
        {
          "id": "840931-0",
          "title": "Yes",
          "price": 0.415
        },
        {
          "id": "840931-1",
          "title": "No",
          "price": 0.585
        }
      ],
      "volume": 1081161.2079079924,
      "liquidity": 1674426.7884,
      "lastUpdated": "2026-07-16T03:41:25.650Z"
    },
    {
      "id": "2774056",
      "question": "Strait of Hormuz traffic returns to normal by August 31?",
      "category": "General",
      "endDate": "2026-08-31T00:00:00Z",
      "yesPrice": 0.115,
      "outcomes": [
        {
          "id": "2774056-0",
          "title": "Yes",
          "price": 0.115
        },
        {
          "id": "2774056-1",
          "title": "No",
          "price": 0.885
        }
      ],
      "volume": 881784.3854690001,
      "liquidity": 251919.4883,
      "lastUpdated": "2026-07-16T03:41:25.650Z"
    },
    {
      "id": "608565",
      "question": "Will Lionel Messi win the 2026 Ballon d'Or?",
      "category": "General",
      "endDate": "2026-10-31T00:00:00Z",
      "yesPrice": 0.4065,
      "outcomes": [
        {
          "id": "608565-0",
          "title": "Yes",
          "price": 0.4065
        },
        {
          "id": "608565-1",
          "title": "No",
          "price": 0.5935
        }
      ],
      "volume": 215465.345656,
      "liquidity": 417240.94431,
      "lastUpdated": "2026-07-16T03:41:25.650Z"
    },
    {
      "id": "2673621",
      "question": "Will NVIDIA be the largest company in the world by market cap on July 31?",
      "category": "General",
      "endDate": "2026-07-31T23:59:00Z",
      "yesPrice": 0.815,
      "outcomes": [
        {
          "id": "2673621-0",
          "title": "Yes",
          "price": 0.815
        },
        {
          "id": "2673621-1",
          "title": "No",
          "price": 0.185
        }
      ],
      "volume": 1294989.176916996,
      "liquidity": 50645.1804,
      "lastUpdated": "2026-07-16T03:41:25.650Z"
    },
    {
      "id": "677407",
      "question": "China x Taiwan military clash before 2027?",
      "category": "General",
      "endDate": "2026-12-31T00:00:00Z",
      "yesPrice": 0.0635,
      "outcomes": [
        {
          "id": "677407-0",
          "title": "Yes",
          "price": 0.0635
        },
        {
          "id": "677407-1",
          "title": "No",
          "price": 0.9365
        }
      ],
      "volume": 2956146.557102005,
      "liquidity": 92479.6564,
      "lastUpdated": "2026-07-16T03:41:25.650Z"
    },
    {
      "id": "2758343",
      "question": "Will Bitcoin dip to $57,500 in July?",
      "category": "General",
      "endDate": "2026-08-01T04:00:00Z",
      "yesPrice": 0.115,
      "outcomes": [
        {
          "id": "2758343-0",
          "title": "Yes",
          "price": 0.115
        },
        {
          "id": "2758343-1",
          "title": "No",
          "price": 0.885
        }
      ],
      "volume": 740895.0862559997,
      "liquidity": 77865.7013,
      "lastUpdated": "2026-07-16T03:41:25.650Z"
    },
    {
      "id": "2730118",
      "question": "Will WTI Crude Oil (WTI) hit (HIGH) $85 in July?",
      "category": "General",
      "endDate": "2026-08-01T03:59:59.999Z",
      "yesPrice": 0.495,
      "outcomes": [
        {
          "id": "2730118-0",
          "title": "Yes",
          "price": 0.495
        },
        {
          "id": "2730118-1",
          "title": "No",
          "price": 0.505
        }
      ],
      "volume": 891323.8619029971,
      "liquidity": 39128.5264,
      "lastUpdated": "2026-07-16T03:41:25.650Z"
    },
    {
      "id": "2470849",
      "question": "President Trump to Attend World Cup Final?",
      "category": "General",
      "endDate": "2026-07-20T03:59:00Z",
      "yesPrice": 0.925,
      "outcomes": [
        {
          "id": "2470849-0",
          "title": "Yes",
          "price": 0.925
        },
        {
          "id": "2470849-1",
          "title": "No",
          "price": 0.075
        }
      ],
      "volume": 566099.7475789991,
      "liquidity": 37007.42836,
      "lastUpdated": "2026-07-16T03:41:25.650Z"
    },
    {
      "id": "2907500",
      "question": "Major League Cricket: Washington Freedom vs Mi New York",
      "category": "General",
      "endDate": "2026-07-22T21:30:00Z",
      "yesPrice": 0.13,
      "outcomes": [
        {
          "id": "2907500-0",
          "title": "Washington Freedom",
          "price": 0.13
        },
        {
          "id": "2907500-1",
          "title": "Mi New York",
          "price": 0.87
        }
      ],
      "volume": 88268.26926899998,
      "liquidity": 137707.0767,
      "lastUpdated": "2026-07-16T03:41:25.650Z"
    },
    {
      "id": "2936687",
      "question": "Dota 2: Nigma Galaxy vs BetBoom Team (BO3) - Esports World Cup Playoffs",
      "category": "General",
      "endDate": "2026-07-16T17:00:00Z",
      "yesPrice": 0.335,
      "outcomes": [
        {
          "id": "2936687-0",
          "title": "Nigma Galaxy",
          "price": 0.335
        },
        {
          "id": "2936687-1",
          "title": "BetBoom Team",
          "price": 0.665
        }
      ],
      "volume": 87377.38422399996,
      "liquidity": 79271.0768,
      "lastUpdated": "2026-07-16T03:41:25.650Z"
    },
    {
      "id": "2252244",
      "question": "Will there be no change in Fed interest rates after the September 2026 meeting?",
      "category": "General",
      "endDate": "2026-09-16T00:00:00Z",
      "yesPrice": 0.645,
      "outcomes": [
        {
          "id": "2252244-0",
          "title": "Yes",
          "price": 0.645
        },
        {
          "id": "2252244-1",
          "title": "No",
          "price": 0.355
        }
      ],
      "volume": 667725.8939519997,
      "liquidity": 175367.388,
      "lastUpdated": "2026-07-16T03:41:25.650Z"
    },
    {
      "id": "561239",
      "question": "Will Kamala Harris win the 2028 US Presidential Election?",
      "category": "General",
      "endDate": "2028-11-07T00:00:00Z",
      "yesPrice": 0.051,
      "outcomes": [
        {
          "id": "561239-0",
          "title": "Yes",
          "price": 0.051
        },
        {
          "id": "561239-1",
          "title": "No",
          "price": 0.949
        }
      ],
      "volume": 8432937.620733023,
      "liquidity": 288744.95677,
      "lastUpdated": "2026-07-16T03:41:25.650Z"
    },
    {
      "id": "2431017",
      "question": "Will Rodri win the Golden Ball at the 2026 FIFA World Cup?",
      "category": "General",
      "endDate": "2026-07-20T03:59:00Z",
      "yesPrice": 0.074,
      "outcomes": [
        {
          "id": "2431017-0",
          "title": "Yes",
          "price": 0.074
        },
        {
          "id": "2431017-1",
          "title": "No",
          "price": 0.926
        }
      ],
      "volume": 2431035.1771100084,
      "liquidity": 68831.18763,
      "lastUpdated": "2026-07-16T03:41:25.650Z"
    },
    {
      "id": "2555351",
      "question": "Israel closes its airspace by July 31?",
      "category": "General",
      "endDate": "2026-07-31T00:00:00Z",
      "yesPrice": 0.115,
      "outcomes": [
        {
          "id": "2555351-0",
          "title": "Yes",
          "price": 0.115
        },
        {
          "id": "2555351-1",
          "title": "No",
          "price": 0.885
        }
      ],
      "volume": 1510796.4936940032,
      "liquidity": 76025.7797,
      "lastUpdated": "2026-07-16T03:41:25.650Z"
    },
    {
      "id": "1931121",
      "question": "Will LeBron James play for the Philadelphia 76ers in 2026-27?",
      "category": "General",
      "endDate": "2026-10-31T03:59:00Z",
      "yesPrice": 0.1435,
      "outcomes": [
        {
          "id": "1931121-0",
          "title": "Yes",
          "price": 0.1435
        },
        {
          "id": "1931121-1",
          "title": "No",
          "price": 0.8565
        }
      ],
      "volume": 1248810.9280330003,
      "liquidity": 29005.14641,
      "lastUpdated": "2026-07-16T03:41:25.650Z"
    },
    {
      "id": "2118801",
      "question": "Will the Fed Pause–Pause–Pause in the next three decisions (Jun–Jul–Sep)?",
      "category": "General",
      "endDate": "2026-09-16T00:00:00Z",
      "yesPrice": 0.68,
      "outcomes": [
        {
          "id": "2118801-0",
          "title": "Yes",
          "price": 0.68
        },
        {
          "id": "2118801-1",
          "title": "No",
          "price": 0.32
        }
      ],
      "volume": 172414.18638999993,
      "liquidity": 101604.9742,
      "lastUpdated": "2026-07-16T03:41:25.650Z"
    },
    {
      "id": "2832147",
      "question": "Will Count Binface win the Clacton by-election?",
      "category": "General",
      "endDate": "2027-06-30T23:59:00Z",
      "yesPrice": 0.0385,
      "outcomes": [
        {
          "id": "2832147-0",
          "title": "Yes",
          "price": 0.0385
        },
        {
          "id": "2832147-1",
          "title": "No",
          "price": 0.9615
        }
      ],
      "volume": 1462409.381312998,
      "liquidity": 216001.96378,
      "lastUpdated": "2026-07-16T03:41:25.650Z"
    },
    {
      "id": "2866810",
      "question": "NBA Summer League: LA Clippers vs. Washington Wizards",
      "category": "General",
      "endDate": "2026-07-16T02:30:00Z",
      "yesPrice": 0.725,
      "outcomes": [
        {
          "id": "2866810-0",
          "title": "LA Clippers",
          "price": 0.725
        },
        {
          "id": "2866810-1",
          "title": "Washington Wizards",
          "price": 0.275
        }
      ],
      "volume": 81425.095724,
      "liquidity": 90354.9041,
      "lastUpdated": "2026-07-16T03:41:25.650Z"
    },
    {
      "id": "687642",
      "question": "China x Japan military clash before 2027?",
      "category": "General",
      "endDate": "2026-12-31T00:00:00Z",
      "yesPrice": 0.075,
      "outcomes": [
        {
          "id": "687642-0",
          "title": "Yes",
          "price": 0.075
        },
        {
          "id": "687642-1",
          "title": "No",
          "price": 0.925
        }
      ],
      "volume": 982645.7927390028,
      "liquidity": 57845.9374,
      "lastUpdated": "2026-07-16T03:41:25.650Z"
    },
    {
      "id": "2646850",
      "question": "US x Iran diplomatic meeting by July 31, 2026?",
      "category": "General",
      "endDate": "2026-07-31T23:59:00Z",
      "yesPrice": 0.245,
      "outcomes": [
        {
          "id": "2646850-0",
          "title": "Yes",
          "price": 0.245
        },
        {
          "id": "2646850-1",
          "title": "No",
          "price": 0.755
        }
      ],
      "volume": 1178549.3453259952,
      "liquidity": 38146.6244,
      "lastUpdated": "2026-07-16T03:41:25.650Z"
    },
    {
      "id": "2677863",
      "question": "Will WTI Crude Oil (WTI) hit (HIGH) $90 in July?",
      "category": "General",
      "endDate": "2026-08-01T03:59:59.999Z",
      "yesPrice": 0.2465,
      "outcomes": [
        {
          "id": "2677863-0",
          "title": "Yes",
          "price": 0.2465
        },
        {
          "id": "2677863-1",
          "title": "No",
          "price": 0.7535
        }
      ],
      "volume": 582696.4893029997,
      "liquidity": 46122.69282,
      "lastUpdated": "2026-07-16T03:41:25.650Z"
    },
    {
      "id": "2923346",
      "question": "Bitcoin Up or Down on July 16?",
      "category": "General",
      "endDate": "2026-07-16T16:00:00Z",
      "yesPrice": 0.205,
      "outcomes": [
        {
          "id": "2923346-0",
          "title": "Up",
          "price": 0.205
        },
        {
          "id": "2923346-1",
          "title": "Down",
          "price": 0.795
        }
      ],
      "volume": 73873.61705699998,
      "liquidity": 31754.846,
      "lastUpdated": "2026-07-16T03:41:25.650Z"
    },
    {
      "id": "608547",
      "question": "Will Harry Kane win the 2026 Ballon d'Or?",
      "category": "General",
      "endDate": "2026-10-31T00:00:00Z",
      "yesPrice": 0.1715,
      "outcomes": [
        {
          "id": "608547-0",
          "title": "Yes",
          "price": 0.1715
        },
        {
          "id": "608547-1",
          "title": "No",
          "price": 0.8285
        }
      ],
      "volume": 934381.2622120015,
      "liquidity": 78865.91748,
      "lastUpdated": "2026-07-16T03:41:25.650Z"
    },
    {
      "id": "560317",
      "question": "Putin out as President of Russia by December 31, 2026?",
      "category": "General",
      "endDate": "2026-12-31T18:30:00Z",
      "yesPrice": 0.095,
      "outcomes": [
        {
          "id": "560317-0",
          "title": "Yes",
          "price": 0.095
        },
        {
          "id": "560317-1",
          "title": "No",
          "price": 0.905
        }
      ],
      "volume": 17229020.85585108,
      "liquidity": 1170970.1266,
      "lastUpdated": "2026-07-16T03:41:25.650Z"
    },
    {
      "id": "2906929",
      "question": "Will Rory McIlroy win the 2026 The Open Championship?",
      "category": "General",
      "endDate": "2026-07-19T00:00:00Z",
      "yesPrice": 0.075,
      "outcomes": [
        {
          "id": "2906929-0",
          "title": "Yes",
          "price": 0.075
        },
        {
          "id": "2906929-1",
          "title": "No",
          "price": 0.925
        }
      ],
      "volume": 90006.872785,
      "liquidity": 238834.9478,
      "lastUpdated": "2026-07-16T03:41:25.650Z"
    },
    {
      "id": "2934802",
      "question": "LoL: Hanwha Life Esports vs JD Gaming (BO1) - Esports World Cup Group D",
      "category": "General",
      "endDate": "2026-07-16T16:10:00Z",
      "yesPrice": 0.725,
      "outcomes": [
        {
          "id": "2934802-0",
          "title": "Hanwha Life Esports",
          "price": 0.725
        },
        {
          "id": "2934802-1",
          "title": "JD Gaming",
          "price": 0.275
        }
      ],
      "volume": 71034.14255600012,
      "liquidity": 152291.0944,
      "lastUpdated": "2026-07-16T03:41:25.650Z"
    },
    {
      "id": "2758344",
      "question": "Will Bitcoin dip to $55,000 in July?",
      "category": "General",
      "endDate": "2026-08-01T04:00:00Z",
      "yesPrice": 0.0475,
      "outcomes": [
        {
          "id": "2758344-0",
          "title": "Yes",
          "price": 0.0475
        },
        {
          "id": "2758344-1",
          "title": "No",
          "price": 0.9525
        }
      ],
      "volume": 469447.0413900003,
      "liquidity": 92921.57389,
      "lastUpdated": "2026-07-16T03:41:25.650Z"
    },
    {
      "id": "2170255",
      "question": "Bab el-Mandeb Strait effectively closed by September 30?",
      "category": "General",
      "endDate": "2026-04-30T00:00:00Z",
      "yesPrice": 0.175,
      "outcomes": [
        {
          "id": "2170255-0",
          "title": "Yes",
          "price": 0.175
        },
        {
          "id": "2170255-1",
          "title": "No",
          "price": 0.825
        }
      ],
      "volume": 920253.8033700003,
      "liquidity": 80667.403,
      "lastUpdated": "2026-07-16T03:41:25.651Z"
    },
    {
      "id": "2632929",
      "question": "Will Shabana Mahmood be the next Chancellor of the Exchequer of the UK in 2026?",
      "category": "General",
      "endDate": "2026-12-31T23:59:00Z",
      "yesPrice": 0.869,
      "outcomes": [
        {
          "id": "2632929-0",
          "title": "Yes",
          "price": 0.869
        },
        {
          "id": "2632929-1",
          "title": "No",
          "price": 0.131
        }
      ],
      "volume": 221570.11526299984,
      "liquidity": 15177.45757,
      "lastUpdated": "2026-07-16T03:41:25.651Z"
    }
  ],
  "lastUpdated": "2026-07-16T03:41:33.827Z"
}